RubyOnRailsJiaocheng/README.md
RubyOnRailsJiaocheng/__init__.py
RubyOnRailsJiaocheng/__main__.py
RubyOnRailsJiaocheng/file.epub
RubyOnRailsJiaocheng/index.html
RubyOnRailsJiaocheng/css/__init__.py
RubyOnRailsJiaocheng/css/annotations.css
RubyOnRailsJiaocheng/css/main.css
RubyOnRailsJiaocheng/css/normalize.css
RubyOnRailsJiaocheng/css/popup.css
RubyOnRailsJiaocheng/font/__init__.py
RubyOnRailsJiaocheng/font/fontello.eot
RubyOnRailsJiaocheng/font/fontello.svg
RubyOnRailsJiaocheng/font/fontello.ttf
RubyOnRailsJiaocheng/font/fontello.woff
RubyOnRailsJiaocheng/img/__init__.py
RubyOnRailsJiaocheng/img/annotator-glyph-sprite.png
RubyOnRailsJiaocheng/img/annotator-icon-sprite.png
RubyOnRailsJiaocheng/img/apple-touch-icon.png
RubyOnRailsJiaocheng/img/cancelfullscreen.png
RubyOnRailsJiaocheng/img/close.png
RubyOnRailsJiaocheng/img/fullscreen.png
RubyOnRailsJiaocheng/img/loader.gif
RubyOnRailsJiaocheng/img/menu-icon.png
RubyOnRailsJiaocheng/img/save.png
RubyOnRailsJiaocheng/img/saved.png
RubyOnRailsJiaocheng/img/settings-s.png
RubyOnRailsJiaocheng/img/settings.png
RubyOnRailsJiaocheng/img/star.png
RubyOnRailsJiaocheng/js/__init__.py
RubyOnRailsJiaocheng/js/epub.js
RubyOnRailsJiaocheng/js/epub.min.js
RubyOnRailsJiaocheng/js/epub.min.map
RubyOnRailsJiaocheng/js/hooks.min.js
RubyOnRailsJiaocheng/js/hooks.min.map
RubyOnRailsJiaocheng/js/reader.js
RubyOnRailsJiaocheng/js/reader.js.map
RubyOnRailsJiaocheng/js/reader.min.js
RubyOnRailsJiaocheng/js/reader.min.map
RubyOnRailsJiaocheng/js/hooks/__init__.py
RubyOnRailsJiaocheng/js/hooks/extensions/__init__.py
RubyOnRailsJiaocheng/js/hooks/extensions/highlight.js
RubyOnRailsJiaocheng/js/libs/__init__.py
RubyOnRailsJiaocheng/js/libs/jquery.min.js
RubyOnRailsJiaocheng/js/libs/localforage.min.js
RubyOnRailsJiaocheng/js/libs/screenfull.js
RubyOnRailsJiaocheng/js/libs/screenfull.min.js
RubyOnRailsJiaocheng/js/libs/zip.min.js
RubyOnRailsJiaocheng/js/plugins/__init__.py
RubyOnRailsJiaocheng/js/plugins/hypothesis.js
ruby_on_rails_jiaocheng-2024.3.1.0.dist-info/METADATA
ruby_on_rails_jiaocheng-2024.3.1.0.dist-info/WHEEL
ruby_on_rails_jiaocheng-2024.3.1.0.dist-info/entry_points.txt
ruby_on_rails_jiaocheng-2024.3.1.0.dist-info/top_level.txt
ruby_on_rails_jiaocheng-2024.3.1.0.dist-info/RECORD
